foldback/__init__.py
foldback/nagios/__init__.py
foldback/nagios/plugin.py
foldback-1.2.7.data/data/lib/foldback/agents/bind-statistics
foldback-1.2.7.data/data/lib/foldback/agents/debian-kernel-version
foldback-1.2.7.data/data/lib/foldback/agents/freebsd-kernel-version
foldback-1.2.7.data/data/lib/foldback/agents/freebsd-temperatures
foldback-1.2.7.data/data/lib/foldback/plugins/check-debian-kernel-version
foldback-1.2.7.data/data/lib/foldback/plugins/check-dns-delegation
foldback-1.2.7.data/data/lib/foldback/plugins/check-dns-resolver
foldback-1.2.7.data/data/lib/foldback/plugins/check-domain-expiration
foldback-1.2.7.data/data/lib/foldback/plugins/check-freebsd-kernel-version
foldback-1.2.7.data/data/lib/foldback/plugins/check-freebsd-updates
foldback-1.2.7.data/data/lib/foldback/plugins/check-mail-aliases
foldback-1.2.7.data/data/lib/foldback/plugins/check-nfs-shares
foldback-1.2.7.data/data/lib/foldback/plugins/check-printer
foldback-1.2.7.data/data/lib/foldback/plugins/check-snmp-process-status
foldback-1.2.7.data/data/lib/foldback/plugins/check-ubnt-upgrades
foldback-1.2.7.data/data/share/foldback/commands.cfg
foldback-1.2.7.dist-info/DESCRIPTION.rst
foldback-1.2.7.dist-info/METADATA
foldback-1.2.7.dist-info/RECORD
foldback-1.2.7.dist-info/WHEEL
foldback-1.2.7.dist-info/metadata.json
foldback-1.2.7.dist-info/top_level.txt
