Metadata-Version: 2.0
Name: foldback
Version: 1.2.7
Summary: Network/System monitoring plugins for nagios
Home-page: http://tuohela.net/packages/foldback
Author: Ilkka Tuohela
Author-email: hile@iki.fi
License: PSF
Keywords: nagios network monitoring
Platform: UNKNOWN
Requires-Dist: BeautifulSoup
Requires-Dist: requests
Requires-Dist: seine (>=3.2.0)
Requires-Dist: systematic (>=4.4.1)
